[
  {
    "id_adu": "15",
    "Fecha": "2015/01",
    "Monto de Exportacion": 138794857,
    "Volumen de Importacion": 80,
    "Clave": "26",
    "Tipo_Frontera": "NORTE",
    "Aduana": "Puerto Palomas",
    "Color": "#b2beb5",
    "Volumen de Exportacion": null,
    "Monto de Importacion": null
  },
  {
    "id_adu": "15",
    "Fecha": "2005/01",
    "Monto de Exportacion": 8438316,
    "Volumen de Importacion": 381,
    "Clave": "26",
    "Tipo_Frontera": "NORTE",
    "Aduana": "Puerto Palomas",
    "Color": "#b2beb5",
    "Volumen de Exportacion": null,
    "Monto de Importacion": null
  },
  {
    "id_adu": "15",
    "Fecha": "2005/02",
    "Monto de Exportacion": 9096297,
    "Volumen de Importacion": 332,
    "Clave": "26",
    "Tipo_Frontera": "NORTE",
    "Aduana": "Puerto Palomas",
    "Color": "#b2beb5",
    "Volumen de Exportacion": null,
    "Monto de Importacion": null
  },
  {
    "id_adu": "15",
    "Fecha": "2005/03",
    "Monto de Exportacion": 21666283,
    "Volumen de Importacion": 369,
    "Clave": "26",
    "Tipo_Frontera": "NORTE",
    "Aduana": "Puerto Palomas",
    "Color": "#b2beb5",
    "Volumen de Exportacion": null,
    "Monto de Importacion": null
  },
  {
    "id_adu": "15",
    "Fecha": "2005/04",
    "Monto de Exportacion": 11014387,
    "Volumen de Importacion": 324,
    "Clave": "26",
    "Tipo_Frontera": "NORTE",
    "Aduana": "Puerto Palomas",
    "Color": "#b2beb5",
    "Volumen de Exportacion": null,
    "Monto de Importacion": null
  },
  {
    "id_adu": "15",
    "Fecha": "2005/05",
    "Monto de Exportacion": 18560730,
    "Volumen de Importacion": 365,
    "Clave": "26",
    "Tipo_Frontera": "NORTE",
    "Aduana": "Puerto Palomas",
    "Color": "#b2beb5",
    "Volumen de Exportacion": null,
    "Monto de Importacion": null
  },
  {
    "id_adu": "15",
    "Fecha": "2005/06",
    "Monto de Exportacion": 15979785,
    "Volumen de Importacion": 378,
    "Clave": "26",
    "Tipo_Frontera": "NORTE",
    "Aduana": "Puerto Palomas",
    "Color": "#b2beb5",
    "Volumen de Exportacion": null,
    "Monto de Importacion": null
  },
  {
    "id_adu": "15",
    "Fecha": "2005/07",
    "Monto de Exportacion": 16570689,
    "Volumen de Importacion": 350,
    "Clave": "26",
    "Tipo_Frontera": "NORTE",
    "Aduana": "Puerto Palomas",
    "Color": "#b2beb5",
    "Volumen de Exportacion": null,
    "Monto de Importacion": null
  },
  {
    "id_adu": "15",
    "Fecha": "2005/08",
    "Monto de Exportacion": 16068817,
    "Volumen de Importacion": 391,
    "Clave": "26",
    "Tipo_Frontera": "NORTE",
    "Aduana": "Puerto Palomas",
    "Color": "#b2beb5",
    "Volumen de Exportacion": null,
    "Monto de Importacion": null
  },
  {
    "id_adu": "15",
    "Fecha": "2005/09",
    "Monto de Exportacion": 21435622,
    "Volumen de Importacion": 307,
    "Clave": "26",
    "Tipo_Frontera": "NORTE",
    "Aduana": "Puerto Palomas",
    "Color": "#b2beb5",
    "Volumen de Exportacion": null,
    "Monto de Importacion": null
  },
  {
    "id_adu": "15",
    "Fecha": "2005/10",
    "Monto de Exportacion": 37810373,
    "Volumen de Importacion": 397,
    "Clave": "26",
    "Tipo_Frontera": "NORTE",
    "Aduana": "Puerto Palomas",
    "Color": "#b2beb5",
    "Volumen de Exportacion": null,
    "Monto de Importacion": null
  },
  {
    "id_adu": "15",
    "Fecha": "2005/11",
    "Monto de Exportacion": 44951356,
    "Volumen de Importacion": 637,
    "Clave": "26",
    "Tipo_Frontera": "NORTE",
    "Aduana": "Puerto Palomas",
    "Color": "#b2beb5",
    "Volumen de Exportacion": null,
    "Monto de Importacion": null
  },
  {
    "id_adu": "15",
    "Fecha": "2005/12",
    "Monto de Exportacion": 33523355,
    "Volumen de Importacion": 543,
    "Clave": "26",
    "Tipo_Frontera": "NORTE",
    "Aduana": "Puerto Palomas",
    "Color": "#b2beb5",
    "Volumen de Exportacion": null,
    "Monto de Importacion": null
  },
  {
    "id_adu": "15",
    "Fecha": "2006/01",
    "Monto de Exportacion": 7876417,
    "Volumen de Importacion": 357,
    "Clave": "26",
    "Tipo_Frontera": "NORTE",
    "Aduana": "Puerto Palomas",
    "Color": "#b2beb5",
    "Volumen de Exportacion": null,
    "Monto de Importacion": null
  },
  {
    "id_adu": "15",
    "Fecha": "2006/02",
    "Monto de Exportacion": 30076015,
    "Volumen de Importacion": 404,
    "Clave": "26",
    "Tipo_Frontera": "NORTE",
    "Aduana": "Puerto Palomas",
    "Color": "#b2beb5",
    "Volumen de Exportacion": null,
    "Monto de Importacion": null
  },
  {
    "id_adu": "15",
    "Fecha": "2006/03",
    "Monto de Exportacion": 25317026,
    "Volumen de Importacion": 400,
    "Clave": "26",
    "Tipo_Frontera": "NORTE",
    "Aduana": "Puerto Palomas",
    "Color": "#b2beb5",
    "Volumen de Exportacion": null,
    "Monto de Importacion": null
  },
  {
    "id_adu": "15",
    "Fecha": "2006/04",
    "Monto de Exportacion": 23626428,
    "Volumen de Importacion": 309,
    "Clave": "26",
    "Tipo_Frontera": "NORTE",
    "Aduana": "Puerto Palomas",
    "Color": "#b2beb5",
    "Volumen de Exportacion": null,
    "Monto de Importacion": null
  },
  {
    "id_adu": "15",
    "Fecha": "2006/05",
    "Monto de Exportacion": 13333903,
    "Volumen de Importacion": 377,
    "Clave": "26",
    "Tipo_Frontera": "NORTE",
    "Aduana": "Puerto Palomas",
    "Color": "#b2beb5",
    "Volumen de Exportacion": null,
    "Monto de Importacion": null
  },
  {
    "id_adu": "15",
    "Fecha": "2006/06",
    "Monto de Exportacion": 7723504,
    "Volumen de Importacion": 464,
    "Clave": "26",
    "Tipo_Frontera": "NORTE",
    "Aduana": "Puerto Palomas",
    "Color": "#b2beb5",
    "Volumen de Exportacion": null,
    "Monto de Importacion": null
  },
  {
    "id_adu": "15",
    "Fecha": "2006/07",
    "Monto de Exportacion": 6567072,
    "Volumen de Importacion": 471,
    "Clave": "26",
    "Tipo_Frontera": "NORTE",
    "Aduana": "Puerto Palomas",
    "Color": "#b2beb5",
    "Volumen de Exportacion": null,
    "Monto de Importacion": null
  },
  {
    "id_adu": "15",
    "Fecha": "2006/08",
    "Monto de Exportacion": 20601683,
    "Volumen de Importacion": 646,
    "Clave": "26",
    "Tipo_Frontera": "NORTE",
    "Aduana": "Puerto Palomas",
    "Color": "#b2beb5",
    "Volumen de Exportacion": null,
    "Monto de Importacion": null
  },
  {
    "id_adu": "15",
    "Fecha": "2006/09",
    "Monto de Exportacion": 34336299,
    "Volumen de Importacion": 662,
    "Clave": "26",
    "Tipo_Frontera": "NORTE",
    "Aduana": "Puerto Palomas",
    "Color": "#b2beb5",
    "Volumen de Exportacion": null,
    "Monto de Importacion": null
  },
  {
    "id_adu": "15",
    "Fecha": "2006/10",
    "Monto de Exportacion": 46388096,
    "Volumen de Importacion": 805,
    "Clave": "26",
    "Tipo_Frontera": "NORTE",
    "Aduana": "Puerto Palomas",
    "Color": "#b2beb5",
    "Volumen de Exportacion": null,
    "Monto de Importacion": null
  },
  {
    "id_adu": "15",
    "Fecha": "2006/11",
    "Monto de Exportacion": 36572726,
    "Volumen de Importacion": 1299,
    "Clave": "26",
    "Tipo_Frontera": "NORTE",
    "Aduana": "Puerto Palomas",
    "Color": "#b2beb5",
    "Volumen de Exportacion": null,
    "Monto de Importacion": null
  },
  {
    "id_adu": "15",
    "Fecha": "2006/12",
    "Monto de Exportacion": 22013756,
    "Volumen de Importacion": 1265,
    "Clave": "26",
    "Tipo_Frontera": "NORTE",
    "Aduana": "Puerto Palomas",
    "Color": "#b2beb5",
    "Volumen de Exportacion": null,
    "Monto de Importacion": null
  },
  {
    "id_adu": "15",
    "Fecha": "2007/01",
    "Monto de Exportacion": 6681926,
    "Volumen de Importacion": 852,
    "Clave": "26",
    "Tipo_Frontera": "NORTE",
    "Aduana": "Puerto Palomas",
    "Color": "#b2beb5",
    "Volumen de Exportacion": null,
    "Monto de Importacion": null
  },
  {
    "id_adu": "15",
    "Fecha": "2007/02",
    "Monto de Exportacion": 7164370,
    "Volumen de Importacion": 994,
    "Clave": "26",
    "Tipo_Frontera": "NORTE",
    "Aduana": "Puerto Palomas",
    "Color": "#b2beb5",
    "Volumen de Exportacion": null,
    "Monto de Importacion": null
  },
  {
    "id_adu": "15",
    "Fecha": "2007/03",
    "Monto de Exportacion": 21477164,
    "Volumen de Importacion": 1363,
    "Clave": "26",
    "Tipo_Frontera": "NORTE",
    "Aduana": "Puerto Palomas",
    "Color": "#b2beb5",
    "Volumen de Exportacion": null,
    "Monto de Importacion": null
  },
  {
    "id_adu": "15",
    "Fecha": "2007/04",
    "Monto de Exportacion": 9591108,
    "Volumen de Importacion": 1355,
    "Clave": "26",
    "Tipo_Frontera": "NORTE",
    "Aduana": "Puerto Palomas",
    "Color": "#b2beb5",
    "Volumen de Exportacion": null,
    "Monto de Importacion": null
  },
  {
    "id_adu": "15",
    "Fecha": "2007/05",
    "Monto de Exportacion": 12056260,
    "Volumen de Importacion": 1362,
    "Clave": "26",
    "Tipo_Frontera": "NORTE",
    "Aduana": "Puerto Palomas",
    "Color": "#b2beb5",
    "Volumen de Exportacion": null,
    "Monto de Importacion": null
  },
  {
    "id_adu": "15",
    "Fecha": "2007/06",
    "Monto de Exportacion": 11149973,
    "Volumen de Importacion": 1287,
    "Clave": "26",
    "Tipo_Frontera": "NORTE",
    "Aduana": "Puerto Palomas",
    "Color": "#b2beb5",
    "Volumen de Exportacion": null,
    "Monto de Importacion": null
  },
  {
    "id_adu": "15",
    "Fecha": "2007/07",
    "Monto de Exportacion": 17415693,
    "Volumen de Importacion": 1068,
    "Clave": "26",
    "Tipo_Frontera": "NORTE",
    "Aduana": "Puerto Palomas",
    "Color": "#b2beb5",
    "Volumen de Exportacion": null,
    "Monto de Importacion": null
  },
  {
    "id_adu": "15",
    "Fecha": "2007/08",
    "Monto de Exportacion": 18650313,
    "Volumen de Importacion": 787,
    "Clave": "26",
    "Tipo_Frontera": "NORTE",
    "Aduana": "Puerto Palomas",
    "Color": "#b2beb5",
    "Volumen de Exportacion": null,
    "Monto de Importacion": null
  },
  {
    "id_adu": "15",
    "Fecha": "2007/09",
    "Monto de Exportacion": 29270801,
    "Volumen de Importacion": 664,
    "Clave": "26",
    "Tipo_Frontera": "NORTE",
    "Aduana": "Puerto Palomas",
    "Color": "#b2beb5",
    "Volumen de Exportacion": null,
    "Monto de Importacion": null
  },
  {
    "id_adu": "15",
    "Fecha": "2007/10",
    "Monto de Exportacion": 80160820,
    "Volumen de Importacion": 937,
    "Clave": "26",
    "Tipo_Frontera": "NORTE",
    "Aduana": "Puerto Palomas",
    "Color": "#b2beb5",
    "Volumen de Exportacion": null,
    "Monto de Importacion": null
  },
  {
    "id_adu": "15",
    "Fecha": "2007/11",
    "Monto de Exportacion": 80070071,
    "Volumen de Importacion": 1141,
    "Clave": "26",
    "Tipo_Frontera": "NORTE",
    "Aduana": "Puerto Palomas",
    "Color": "#b2beb5",
    "Volumen de Exportacion": null,
    "Monto de Importacion": null
  },
  {
    "id_adu": "15",
    "Fecha": "2007/12",
    "Monto de Exportacion": 23305608,
    "Volumen de Importacion": 1179,
    "Clave": "26",
    "Tipo_Frontera": "NORTE",
    "Aduana": "Puerto Palomas",
    "Color": "#b2beb5",
    "Volumen de Exportacion": null,
    "Monto de Importacion": null
  },
  {
    "id_adu": "15",
    "Fecha": "2008/01",
    "Monto de Exportacion": 5484725,
    "Volumen de Importacion": 562,
    "Clave": "26",
    "Tipo_Frontera": "NORTE",
    "Aduana": "Puerto Palomas",
    "Color": "#b2beb5",
    "Volumen de Exportacion": null,
    "Monto de Importacion": null
  },
  {
    "id_adu": "15",
    "Fecha": "2008/02",
    "Monto de Exportacion": 5295248,
    "Volumen de Importacion": 1790,
    "Clave": "26",
    "Tipo_Frontera": "NORTE",
    "Aduana": "Puerto Palomas",
    "Color": "#b2beb5",
    "Volumen de Exportacion": null,
    "Monto de Importacion": null
  },
  {
    "id_adu": "15",
    "Fecha": "2008/03",
    "Monto de Exportacion": 10494981,
    "Volumen de Importacion": 1562,
    "Clave": "26",
    "Tipo_Frontera": "NORTE",
    "Aduana": "Puerto Palomas",
    "Color": "#b2beb5",
    "Volumen de Exportacion": null,
    "Monto de Importacion": null
  },
  {
    "id_adu": "15",
    "Fecha": "2008/04",
    "Monto de Exportacion": 10414437,
    "Volumen de Importacion": 307,
    "Clave": "26",
    "Tipo_Frontera": "NORTE",
    "Aduana": "Puerto Palomas",
    "Color": "#b2beb5",
    "Volumen de Exportacion": null,
    "Monto de Importacion": null
  },
  {
    "id_adu": "15",
    "Fecha": "2008/05",
    "Monto de Exportacion": 8965845,
    "Volumen de Importacion": 298,
    "Clave": "26",
    "Tipo_Frontera": "NORTE",
    "Aduana": "Puerto Palomas",
    "Color": "#b2beb5",
    "Volumen de Exportacion": null,
    "Monto de Importacion": null
  },
  {
    "id_adu": "15",
    "Fecha": "2008/06",
    "Monto de Exportacion": 12209302,
    "Volumen de Importacion": 304,
    "Clave": "26",
    "Tipo_Frontera": "NORTE",
    "Aduana": "Puerto Palomas",
    "Color": "#b2beb5",
    "Volumen de Exportacion": null,
    "Monto de Importacion": null
  },
  {
    "id_adu": "15",
    "Fecha": "2008/07",
    "Monto de Exportacion": 19392096,
    "Volumen de Importacion": 367,
    "Clave": "26",
    "Tipo_Frontera": "NORTE",
    "Aduana": "Puerto Palomas",
    "Color": "#b2beb5",
    "Volumen de Exportacion": null,
    "Monto de Importacion": null
  },
  {
    "id_adu": "15",
    "Fecha": "2008/08",
    "Monto de Exportacion": 19887432,
    "Volumen de Importacion": 310,
    "Clave": "26",
    "Tipo_Frontera": "NORTE",
    "Aduana": "Puerto Palomas",
    "Color": "#b2beb5",
    "Volumen de Exportacion": null,
    "Monto de Importacion": null
  },
  {
    "id_adu": "15",
    "Fecha": "2008/09",
    "Monto de Exportacion": 32889116,
    "Volumen de Importacion": 309,
    "Clave": "26",
    "Tipo_Frontera": "NORTE",
    "Aduana": "Puerto Palomas",
    "Color": "#b2beb5",
    "Volumen de Exportacion": null,
    "Monto de Importacion": null
  },
  {
    "id_adu": "15",
    "Fecha": "2008/10",
    "Monto de Exportacion": 56466432,
    "Volumen de Importacion": 333,
    "Clave": "26",
    "Tipo_Frontera": "NORTE",
    "Aduana": "Puerto Palomas",
    "Color": "#b2beb5",
    "Volumen de Exportacion": null,
    "Monto de Importacion": null
  },
  {
    "id_adu": "15",
    "Fecha": "2008/11",
    "Monto de Exportacion": 85126609,
    "Volumen de Importacion": 411,
    "Clave": "26",
    "Tipo_Frontera": "NORTE",
    "Aduana": "Puerto Palomas",
    "Color": "#b2beb5",
    "Volumen de Exportacion": null,
    "Monto de Importacion": null
  },
  {
    "id_adu": "15",
    "Fecha": "2008/12",
    "Monto de Exportacion": 28811641,
    "Volumen de Importacion": 472,
    "Clave": "26",
    "Tipo_Frontera": "NORTE",
    "Aduana": "Puerto Palomas",
    "Color": "#b2beb5",
    "Volumen de Exportacion": null,
    "Monto de Importacion": null
  },
  {
    "id_adu": "15",
    "Fecha": "2009/01",
    "Monto de Exportacion": 5341872,
    "Volumen de Importacion": 86,
    "Clave": "26",
    "Tipo_Frontera": "NORTE",
    "Aduana": "Puerto Palomas",
    "Color": "#b2beb5",
    "Volumen de Exportacion": null,
    "Monto de Importacion": null
  },
  {
    "id_adu": "15",
    "Fecha": "2009/02",
    "Monto de Exportacion": 16376669,
    "Volumen de Importacion": 130,
    "Clave": "26",
    "Tipo_Frontera": "NORTE",
    "Aduana": "Puerto Palomas",
    "Color": "#b2beb5",
    "Volumen de Exportacion": null,
    "Monto de Importacion": null
  },
  {
    "id_adu": "15",
    "Fecha": "2009/03",
    "Monto de Exportacion": 20776611,
    "Volumen de Importacion": 157,
    "Clave": "26",
    "Tipo_Frontera": "NORTE",
    "Aduana": "Puerto Palomas",
    "Color": "#b2beb5",
    "Volumen de Exportacion": null,
    "Monto de Importacion": null
  },
  {
    "id_adu": "15",
    "Fecha": "2009/04",
    "Monto de Exportacion": 17220203,
    "Volumen de Importacion": 117,
    "Clave": "26",
    "Tipo_Frontera": "NORTE",
    "Aduana": "Puerto Palomas",
    "Color": "#b2beb5",
    "Volumen de Exportacion": null,
    "Monto de Importacion": null
  },
  {
    "id_adu": "15",
    "Fecha": "2009/05",
    "Monto de Exportacion": 16010501,
    "Volumen de Importacion": 150,
    "Clave": "26",
    "Tipo_Frontera": "NORTE",
    "Aduana": "Puerto Palomas",
    "Color": "#b2beb5",
    "Volumen de Exportacion": null,
    "Monto de Importacion": null
  },
  {
    "id_adu": "15",
    "Fecha": "2009/06",
    "Monto de Exportacion": 20354865,
    "Volumen de Importacion": 186,
    "Clave": "26",
    "Tipo_Frontera": "NORTE",
    "Aduana": "Puerto Palomas",
    "Color": "#b2beb5",
    "Volumen de Exportacion": null,
    "Monto de Importacion": null
  },
  {
    "id_adu": "15",
    "Fecha": "2009/07",
    "Monto de Exportacion": 15254919,
    "Volumen de Importacion": 152,
    "Clave": "26",
    "Tipo_Frontera": "NORTE",
    "Aduana": "Puerto Palomas",
    "Color": "#b2beb5",
    "Volumen de Exportacion": null,
    "Monto de Importacion": null
  },
  {
    "id_adu": "15",
    "Fecha": "2009/08",
    "Monto de Exportacion": 33090997,
    "Volumen de Importacion": 161,
    "Clave": "26",
    "Tipo_Frontera": "NORTE",
    "Aduana": "Puerto Palomas",
    "Color": "#b2beb5",
    "Volumen de Exportacion": null,
    "Monto de Importacion": null
  },
  {
    "id_adu": "15",
    "Fecha": "2009/09",
    "Monto de Exportacion": 65659460,
    "Volumen de Importacion": 133,
    "Clave": "26",
    "Tipo_Frontera": "NORTE",
    "Aduana": "Puerto Palomas",
    "Color": "#b2beb5",
    "Volumen de Exportacion": null,
    "Monto de Importacion": null
  },
  {
    "id_adu": "15",
    "Fecha": "2009/10",
    "Monto de Exportacion": 81354776,
    "Volumen de Importacion": 214,
    "Clave": "26",
    "Tipo_Frontera": "NORTE",
    "Aduana": "Puerto Palomas",
    "Color": "#b2beb5",
    "Volumen de Exportacion": null,
    "Monto de Importacion": null
  },
  {
    "id_adu": "15",
    "Fecha": "2009/11",
    "Monto de Exportacion": 96854772,
    "Volumen de Importacion": 192,
    "Clave": "26",
    "Tipo_Frontera": "NORTE",
    "Aduana": "Puerto Palomas",
    "Color": "#b2beb5",
    "Volumen de Exportacion": null,
    "Monto de Importacion": null
  },
  {
    "id_adu": "15",
    "Fecha": "2009/12",
    "Monto de Exportacion": 64756753,
    "Volumen de Importacion": 193,
    "Clave": "26",
    "Tipo_Frontera": "NORTE",
    "Aduana": "Puerto Palomas",
    "Color": "#b2beb5",
    "Volumen de Exportacion": null,
    "Monto de Importacion": null
  },
  {
    "id_adu": "15",
    "Fecha": "2010/01",
    "Monto de Exportacion": 14906944,
    "Volumen de Importacion": 123,
    "Clave": "26",
    "Tipo_Frontera": "NORTE",
    "Aduana": "Puerto Palomas",
    "Color": "#b2beb5",
    "Volumen de Exportacion": null,
    "Monto de Importacion": null
  },
  {
    "id_adu": "15",
    "Fecha": "2010/02",
    "Monto de Exportacion": 13972446,
    "Volumen de Importacion": 153,
    "Clave": "26",
    "Tipo_Frontera": "NORTE",
    "Aduana": "Puerto Palomas",
    "Color": "#b2beb5",
    "Volumen de Exportacion": null,
    "Monto de Importacion": null
  },
  {
    "id_adu": "15",
    "Fecha": "2010/03",
    "Monto de Exportacion": 33241247,
    "Volumen de Importacion": 185,
    "Clave": "26",
    "Tipo_Frontera": "NORTE",
    "Aduana": "Puerto Palomas",
    "Color": "#b2beb5",
    "Volumen de Exportacion": null,
    "Monto de Importacion": null
  },
  {
    "id_adu": "15",
    "Fecha": "2010/04",
    "Monto de Exportacion": 10892879,
    "Volumen de Importacion": 128,
    "Clave": "26",
    "Tipo_Frontera": "NORTE",
    "Aduana": "Puerto Palomas",
    "Color": "#b2beb5",
    "Volumen de Exportacion": null,
    "Monto de Importacion": null
  },
  {
    "id_adu": "15",
    "Fecha": "2010/05",
    "Monto de Exportacion": 21793272,
    "Volumen de Importacion": 106,
    "Clave": "26",
    "Tipo_Frontera": "NORTE",
    "Aduana": "Puerto Palomas",
    "Color": "#b2beb5",
    "Volumen de Exportacion": null,
    "Monto de Importacion": null
  },
  {
    "id_adu": "15",
    "Fecha": "2010/06",
    "Monto de Exportacion": 36079613,
    "Volumen de Importacion": 116,
    "Clave": "26",
    "Tipo_Frontera": "NORTE",
    "Aduana": "Puerto Palomas",
    "Color": "#b2beb5",
    "Volumen de Exportacion": null,
    "Monto de Importacion": null
  },
  {
    "id_adu": "15",
    "Fecha": "2010/07",
    "Monto de Exportacion": 21367598,
    "Volumen de Importacion": 120,
    "Clave": "26",
    "Tipo_Frontera": "NORTE",
    "Aduana": "Puerto Palomas",
    "Color": "#b2beb5",
    "Volumen de Exportacion": null,
    "Monto de Importacion": null
  },
  {
    "id_adu": "15",
    "Fecha": "2010/08",
    "Monto de Exportacion": 37888615,
    "Volumen de Importacion": 99,
    "Clave": "26",
    "Tipo_Frontera": "NORTE",
    "Aduana": "Puerto Palomas",
    "Color": "#b2beb5",
    "Volumen de Exportacion": null,
    "Monto de Importacion": null
  },
  {
    "id_adu": "15",
    "Fecha": "2010/09",
    "Monto de Exportacion": 50121554,
    "Volumen de Importacion": 97,
    "Clave": "26",
    "Tipo_Frontera": "NORTE",
    "Aduana": "Puerto Palomas",
    "Color": "#b2beb5",
    "Volumen de Exportacion": null,
    "Monto de Importacion": null
  },
  {
    "id_adu": "15",
    "Fecha": "2010/10",
    "Monto de Exportacion": 83992332,
    "Volumen de Importacion": 110,
    "Clave": "26",
    "Tipo_Frontera": "NORTE",
    "Aduana": "Puerto Palomas",
    "Color": "#b2beb5",
    "Volumen de Exportacion": null,
    "Monto de Importacion": null
  },
  {
    "id_adu": "15",
    "Fecha": "2010/11",
    "Monto de Exportacion": 112756385,
    "Volumen de Importacion": 99,
    "Clave": "26",
    "Tipo_Frontera": "NORTE",
    "Aduana": "Puerto Palomas",
    "Color": "#b2beb5",
    "Volumen de Exportacion": null,
    "Monto de Importacion": null
  },
  {
    "id_adu": "15",
    "Fecha": "2010/12",
    "Monto de Exportacion": 44483550,
    "Volumen de Importacion": 118,
    "Clave": "26",
    "Tipo_Frontera": "NORTE",
    "Aduana": "Puerto Palomas",
    "Color": "#b2beb5",
    "Volumen de Exportacion": null,
    "Monto de Importacion": null
  },
  {
    "id_adu": "15",
    "Fecha": "2011/01",
    "Monto de Exportacion": 18962050,
    "Volumen de Importacion": 96,
    "Clave": "26",
    "Tipo_Frontera": "NORTE",
    "Aduana": "Puerto Palomas",
    "Color": "#b2beb5",
    "Volumen de Exportacion": null,
    "Monto de Importacion": null
  },
  {
    "id_adu": "15",
    "Fecha": "2011/02",
    "Monto de Exportacion": 29508643,
    "Volumen de Importacion": 103,
    "Clave": "26",
    "Tipo_Frontera": "NORTE",
    "Aduana": "Puerto Palomas",
    "Color": "#b2beb5",
    "Volumen de Exportacion": null,
    "Monto de Importacion": null
  },
  {
    "id_adu": "15",
    "Fecha": "2011/03",
    "Monto de Exportacion": 40591516,
    "Volumen de Importacion": 115,
    "Clave": "26",
    "Tipo_Frontera": "NORTE",
    "Aduana": "Puerto Palomas",
    "Color": "#b2beb5",
    "Volumen de Exportacion": null,
    "Monto de Importacion": null
  },
  {
    "id_adu": "15",
    "Fecha": "2011/04",
    "Monto de Exportacion": 15636414,
    "Volumen de Importacion": 91,
    "Clave": "26",
    "Tipo_Frontera": "NORTE",
    "Aduana": "Puerto Palomas",
    "Color": "#b2beb5",
    "Volumen de Exportacion": null,
    "Monto de Importacion": null
  },
  {
    "id_adu": "15",
    "Fecha": "2011/05",
    "Monto de Exportacion": 14709057,
    "Volumen de Importacion": 102,
    "Clave": "26",
    "Tipo_Frontera": "NORTE",
    "Aduana": "Puerto Palomas",
    "Color": "#b2beb5",
    "Volumen de Exportacion": null,
    "Monto de Importacion": null
  },
  {
    "id_adu": "15",
    "Fecha": "2011/06",
    "Monto de Exportacion": 15945098,
    "Volumen de Importacion": 110,
    "Clave": "26",
    "Tipo_Frontera": "NORTE",
    "Aduana": "Puerto Palomas",
    "Color": "#b2beb5",
    "Volumen de Exportacion": null,
    "Monto de Importacion": null
  },
  {
    "id_adu": "15",
    "Fecha": "2011/07",
    "Monto de Exportacion": 31860374,
    "Volumen de Importacion": 101,
    "Clave": "26",
    "Tipo_Frontera": "NORTE",
    "Aduana": "Puerto Palomas",
    "Color": "#b2beb5",
    "Volumen de Exportacion": null,
    "Monto de Importacion": null
  },
  {
    "id_adu": "15",
    "Fecha": "2011/08",
    "Monto de Exportacion": 78497556,
    "Volumen de Importacion": 119,
    "Clave": "26",
    "Tipo_Frontera": "NORTE",
    "Aduana": "Puerto Palomas",
    "Color": "#b2beb5",
    "Volumen de Exportacion": null,
    "Monto de Importacion": null
  },
  {
    "id_adu": "15",
    "Fecha": "2011/09",
    "Monto de Exportacion": 53456274,
    "Volumen de Importacion": 117,
    "Clave": "26",
    "Tipo_Frontera": "NORTE",
    "Aduana": "Puerto Palomas",
    "Color": "#b2beb5",
    "Volumen de Exportacion": null,
    "Monto de Importacion": null
  },
  {
    "id_adu": "15",
    "Fecha": "2011/10",
    "Monto de Exportacion": 58095006,
    "Volumen de Importacion": 144,
    "Clave": "26",
    "Tipo_Frontera": "NORTE",
    "Aduana": "Puerto Palomas",
    "Color": "#b2beb5",
    "Volumen de Exportacion": null,
    "Monto de Importacion": null
  },
  {
    "id_adu": "15",
    "Fecha": "2011/11",
    "Monto de Exportacion": 57905937,
    "Volumen de Importacion": 108,
    "Clave": "26",
    "Tipo_Frontera": "NORTE",
    "Aduana": "Puerto Palomas",
    "Color": "#b2beb5",
    "Volumen de Exportacion": null,
    "Monto de Importacion": null
  },
  {
    "id_adu": "15",
    "Fecha": "2011/12",
    "Monto de Exportacion": 74559963,
    "Volumen de Importacion": 108,
    "Clave": "26",
    "Tipo_Frontera": "NORTE",
    "Aduana": "Puerto Palomas",
    "Color": "#b2beb5",
    "Volumen de Exportacion": null,
    "Monto de Importacion": null
  },
  {
    "id_adu": "15",
    "Fecha": "2012/01",
    "Monto de Exportacion": 32468593,
    "Volumen de Importacion": 81,
    "Clave": "26",
    "Tipo_Frontera": "NORTE",
    "Aduana": "Puerto Palomas",
    "Color": "#b2beb5",
    "Volumen de Exportacion": null,
    "Monto de Importacion": null
  },
  {
    "id_adu": "15",
    "Fecha": "2012/02",
    "Monto de Exportacion": 32293450,
    "Volumen de Importacion": 150,
    "Clave": "26",
    "Tipo_Frontera": "NORTE",
    "Aduana": "Puerto Palomas",
    "Color": "#b2beb5",
    "Volumen de Exportacion": null,
    "Monto de Importacion": null
  },
  {
    "id_adu": "15",
    "Fecha": "2012/03",
    "Monto de Exportacion": 19938470,
    "Volumen de Importacion": 138,
    "Clave": "26",
    "Tipo_Frontera": "NORTE",
    "Aduana": "Puerto Palomas",
    "Color": "#b2beb5",
    "Volumen de Exportacion": null,
    "Monto de Importacion": null
  },
  {
    "id_adu": "15",
    "Fecha": "2012/04",
    "Monto de Exportacion": 14337913,
    "Volumen de Importacion": 112,
    "Clave": "26",
    "Tipo_Frontera": "NORTE",
    "Aduana": "Puerto Palomas",
    "Color": "#b2beb5",
    "Volumen de Exportacion": null,
    "Monto de Importacion": null
  },
  {
    "id_adu": "15",
    "Fecha": "2012/05",
    "Monto de Exportacion": 12264149,
    "Volumen de Importacion": 106,
    "Clave": "26",
    "Tipo_Frontera": "NORTE",
    "Aduana": "Puerto Palomas",
    "Color": "#b2beb5",
    "Volumen de Exportacion": null,
    "Monto de Importacion": null
  },
  {
    "id_adu": "15",
    "Fecha": "2012/06",
    "Monto de Exportacion": 31193635,
    "Volumen de Importacion": 87,
    "Clave": "26",
    "Tipo_Frontera": "NORTE",
    "Aduana": "Puerto Palomas",
    "Color": "#b2beb5",
    "Volumen de Exportacion": null,
    "Monto de Importacion": null
  },
  {
    "id_adu": "15",
    "Fecha": "2012/07",
    "Monto de Exportacion": 41493042,
    "Volumen de Importacion": 102,
    "Clave": "26",
    "Tipo_Frontera": "NORTE",
    "Aduana": "Puerto Palomas",
    "Color": "#b2beb5",
    "Volumen de Exportacion": null,
    "Monto de Importacion": null
  },
  {
    "id_adu": "15",
    "Fecha": "2012/08",
    "Monto de Exportacion": 43261988,
    "Volumen de Importacion": 84,
    "Clave": "26",
    "Tipo_Frontera": "NORTE",
    "Aduana": "Puerto Palomas",
    "Color": "#b2beb5",
    "Volumen de Exportacion": null,
    "Monto de Importacion": null
  },
  {
    "id_adu": "15",
    "Fecha": "2012/09",
    "Monto de Exportacion": 63217691,
    "Volumen de Importacion": 71,
    "Clave": "26",
    "Tipo_Frontera": "NORTE",
    "Aduana": "Puerto Palomas",
    "Color": "#b2beb5",
    "Volumen de Exportacion": null,
    "Monto de Importacion": null
  },
  {
    "id_adu": "15",
    "Fecha": "2012/10",
    "Monto de Exportacion": 77890574,
    "Volumen de Importacion": 93,
    "Clave": "26",
    "Tipo_Frontera": "NORTE",
    "Aduana": "Puerto Palomas",
    "Color": "#b2beb5",
    "Volumen de Exportacion": null,
    "Monto de Importacion": null
  },
  {
    "id_adu": "15",
    "Fecha": "2012/11",
    "Monto de Exportacion": 66194129,
    "Volumen de Importacion": 80,
    "Clave": "26",
    "Tipo_Frontera": "NORTE",
    "Aduana": "Puerto Palomas",
    "Color": "#b2beb5",
    "Volumen de Exportacion": null,
    "Monto de Importacion": null
  },
  {
    "id_adu": "15",
    "Fecha": "2012/12",
    "Monto de Exportacion": 126193530,
    "Volumen de Importacion": 97,
    "Clave": "26",
    "Tipo_Frontera": "NORTE",
    "Aduana": "Puerto Palomas",
    "Color": "#b2beb5",
    "Volumen de Exportacion": null,
    "Monto de Importacion": null
  },
  {
    "id_adu": "15",
    "Fecha": "2013/01",
    "Monto de Exportacion": 12487132,
    "Volumen de Importacion": 96,
    "Clave": "26",
    "Tipo_Frontera": "NORTE",
    "Aduana": "Puerto Palomas",
    "Color": "#b2beb5",
    "Volumen de Exportacion": null,
    "Monto de Importacion": null
  },
  {
    "id_adu": "15",
    "Fecha": "2013/02",
    "Monto de Exportacion": 36885480,
    "Volumen de Importacion": 151,
    "Clave": "26",
    "Tipo_Frontera": "NORTE",
    "Aduana": "Puerto Palomas",
    "Color": "#b2beb5",
    "Volumen de Exportacion": null,
    "Monto de Importacion": null
  },
  {
    "id_adu": "15",
    "Fecha": "2013/03",
    "Monto de Exportacion": 29854972,
    "Volumen de Importacion": 146,
    "Clave": "26",
    "Tipo_Frontera": "NORTE",
    "Aduana": "Puerto Palomas",
    "Color": "#b2beb5",
    "Volumen de Exportacion": null,
    "Monto de Importacion": null
  },
  {
    "id_adu": "15",
    "Fecha": "2013/04",
    "Monto de Exportacion": 19389034,
    "Volumen de Importacion": 172,
    "Clave": "26",
    "Tipo_Frontera": "NORTE",
    "Aduana": "Puerto Palomas",
    "Color": "#b2beb5",
    "Volumen de Exportacion": null,
    "Monto de Importacion": null
  },
  {
    "id_adu": "15",
    "Fecha": "2013/05",
    "Monto de Exportacion": 18460721,
    "Volumen de Importacion": 226,
    "Clave": "26",
    "Tipo_Frontera": "NORTE",
    "Aduana": "Puerto Palomas",
    "Color": "#b2beb5",
    "Volumen de Exportacion": null,
    "Monto de Importacion": null
  },
  {
    "id_adu": "15",
    "Fecha": "2013/06",
    "Monto de Exportacion": 19417617,
    "Volumen de Importacion": 192,
    "Clave": "26",
    "Tipo_Frontera": "NORTE",
    "Aduana": "Puerto Palomas",
    "Color": "#b2beb5",
    "Volumen de Exportacion": null,
    "Monto de Importacion": null
  },
  {
    "id_adu": "15",
    "Fecha": "2013/07",
    "Monto de Exportacion": 40951377,
    "Volumen de Importacion": 222,
    "Clave": "26",
    "Tipo_Frontera": "NORTE",
    "Aduana": "Puerto Palomas",
    "Color": "#b2beb5",
    "Volumen de Exportacion": null,
    "Monto de Importacion": null
  },
  {
    "id_adu": "15",
    "Fecha": "2013/08",
    "Monto de Exportacion": 64490107,
    "Volumen de Importacion": 251,
    "Clave": "26",
    "Tipo_Frontera": "NORTE",
    "Aduana": "Puerto Palomas",
    "Color": "#b2beb5",
    "Volumen de Exportacion": null,
    "Monto de Importacion": null
  },
  {
    "id_adu": "15",
    "Fecha": "2013/09",
    "Monto de Exportacion": 65332475,
    "Volumen de Importacion": 150,
    "Clave": "26",
    "Tipo_Frontera": "NORTE",
    "Aduana": "Puerto Palomas",
    "Color": "#b2beb5",
    "Volumen de Exportacion": null,
    "Monto de Importacion": null
  },
  {
    "id_adu": "15",
    "Fecha": "2013/10",
    "Monto de Exportacion": 112963812,
    "Volumen de Importacion": 196,
    "Clave": "26",
    "Tipo_Frontera": "NORTE",
    "Aduana": "Puerto Palomas",
    "Color": "#b2beb5",
    "Volumen de Exportacion": null,
    "Monto de Importacion": null
  },
  {
    "id_adu": "15",
    "Fecha": "2013/11",
    "Monto de Exportacion": 84007730,
    "Volumen de Importacion": 241,
    "Clave": "26",
    "Tipo_Frontera": "NORTE",
    "Aduana": "Puerto Palomas",
    "Color": "#b2beb5",
    "Volumen de Exportacion": null,
    "Monto de Importacion": null
  },
  {
    "id_adu": "15",
    "Fecha": "2013/12",
    "Monto de Exportacion": 173553171,
    "Volumen de Importacion": 682,
    "Clave": "26",
    "Tipo_Frontera": "NORTE",
    "Aduana": "Puerto Palomas",
    "Color": "#b2beb5",
    "Volumen de Exportacion": null,
    "Monto de Importacion": null
  },
  {
    "id_adu": "15",
    "Fecha": "2014/01",
    "Monto de Exportacion": 35623960,
    "Volumen de Importacion": 426,
    "Clave": "26",
    "Tipo_Frontera": "NORTE",
    "Aduana": "Puerto Palomas",
    "Color": "#b2beb5",
    "Volumen de Exportacion": null,
    "Monto de Importacion": null
  },
  {
    "id_adu": "15",
    "Fecha": "2014/02",
    "Monto de Exportacion": 84523265,
    "Volumen de Importacion": 306,
    "Clave": "26",
    "Tipo_Frontera": "NORTE",
    "Aduana": "Puerto Palomas",
    "Color": "#b2beb5",
    "Volumen de Exportacion": null,
    "Monto de Importacion": null
  },
  {
    "id_adu": "15",
    "Fecha": "2014/03",
    "Monto de Exportacion": 52301882,
    "Volumen de Importacion": 214,
    "Clave": "26",
    "Tipo_Frontera": "NORTE",
    "Aduana": "Puerto Palomas",
    "Color": "#b2beb5",
    "Volumen de Exportacion": null,
    "Monto de Importacion": null
  },
  {
    "id_adu": "15",
    "Fecha": "2014/04",
    "Monto de Exportacion": 104560158,
    "Volumen de Importacion": 234,
    "Clave": "26",
    "Tipo_Frontera": "NORTE",
    "Aduana": "Puerto Palomas",
    "Color": "#b2beb5",
    "Volumen de Exportacion": null,
    "Monto de Importacion": null
  },
  {
    "id_adu": "15",
    "Fecha": "2014/05",
    "Monto de Exportacion": 70687679,
    "Volumen de Importacion": 231,
    "Clave": "26",
    "Tipo_Frontera": "NORTE",
    "Aduana": "Puerto Palomas",
    "Color": "#b2beb5",
    "Volumen de Exportacion": null,
    "Monto de Importacion": null
  },
  {
    "id_adu": "15",
    "Fecha": "2014/06",
    "Monto de Exportacion": 67532306,
    "Volumen de Importacion": 227,
    "Clave": "26",
    "Tipo_Frontera": "NORTE",
    "Aduana": "Puerto Palomas",
    "Color": "#b2beb5",
    "Volumen de Exportacion": null,
    "Monto de Importacion": null
  },
  {
    "id_adu": "15",
    "Fecha": "2014/07",
    "Monto de Exportacion": 73786157,
    "Volumen de Importacion": 275,
    "Clave": "26",
    "Tipo_Frontera": "NORTE",
    "Aduana": "Puerto Palomas",
    "Color": "#b2beb5",
    "Volumen de Exportacion": null,
    "Monto de Importacion": null
  },
  {
    "id_adu": "15",
    "Fecha": "2014/08",
    "Monto de Exportacion": 58247644,
    "Volumen de Importacion": 436,
    "Clave": "26",
    "Tipo_Frontera": "NORTE",
    "Aduana": "Puerto Palomas",
    "Color": "#b2beb5",
    "Volumen de Exportacion": null,
    "Monto de Importacion": null
  },
  {
    "id_adu": "15",
    "Fecha": "2014/09",
    "Monto de Exportacion": 108129693,
    "Volumen de Importacion": 186,
    "Clave": "26",
    "Tipo_Frontera": "NORTE",
    "Aduana": "Puerto Palomas",
    "Color": "#b2beb5",
    "Volumen de Exportacion": null,
    "Monto de Importacion": null
  },
  {
    "id_adu": "15",
    "Fecha": "2014/10",
    "Monto de Exportacion": 183766213,
    "Volumen de Importacion": 477,
    "Clave": "26",
    "Tipo_Frontera": "NORTE",
    "Aduana": "Puerto Palomas",
    "Color": "#b2beb5",
    "Volumen de Exportacion": null,
    "Monto de Importacion": null
  },
  {
    "id_adu": "15",
    "Fecha": "2014/11",
    "Monto de Exportacion": 228779162,
    "Volumen de Importacion": 221,
    "Clave": "26",
    "Tipo_Frontera": "NORTE",
    "Aduana": "Puerto Palomas",
    "Color": "#b2beb5",
    "Volumen de Exportacion": null,
    "Monto de Importacion": null
  },
  {
    "id_adu": "15",
    "Fecha": "2014/12",
    "Monto de Exportacion": 201657597,
    "Volumen de Importacion": 68,
    "Clave": "26",
    "Tipo_Frontera": "NORTE",
    "Aduana": "Puerto Palomas",
    "Color": "#b2beb5",
    "Volumen de Exportacion": null,
    "Monto de Importacion": null
  },
  {
    "id_adu": "54",
    "Fecha": "2015/01",
    "Monto de Exportacion": 138794857,
    "Volumen de Importacion": 80,
    "Clave": "26",
    "Tipo_Frontera": "NORTE",
    "Aduana": "Puerto Palomas",
    "Color": "#ff0800",
    "Volumen de Exportacion": null,
    "Monto de Importacion": null
  },
  {
    "id_adu": "54",
    "Fecha": "2015/02",
    "Monto de Exportacion": 67326084,
    "Volumen de Importacion": 101,
    "Clave": "26",
    "Tipo_Frontera": "NORTE",
    "Aduana": "Puerto Palomas",
    "Color": "#ff0800",
    "Volumen de Exportacion": null,
    "Monto de Importacion": null
  },
  {
    "id_adu": "54",
    "Fecha": "2015/03",
    "Monto de Exportacion": 81091778,
    "Volumen de Importacion": 85,
    "Clave": "26",
    "Tipo_Frontera": "NORTE",
    "Aduana": "Puerto Palomas",
    "Color": "#ff0800",
    "Volumen de Exportacion": null,
    "Monto de Importacion": null
  },
  {
    "id_adu": "54",
    "Fecha": "2015/04",
    "Monto de Exportacion": 125772912,
    "Volumen de Importacion": 63,
    "Clave": "26",
    "Tipo_Frontera": "NORTE",
    "Aduana": "Puerto Palomas",
    "Color": "#ff0800",
    "Volumen de Exportacion": null,
    "Monto de Importacion": null
  },
  {
    "id_adu": "54",
    "Fecha": "2015/05",
    "Monto de Exportacion": 59363183,
    "Volumen de Importacion": 54,
    "Clave": "26",
    "Tipo_Frontera": "NORTE",
    "Aduana": "Puerto Palomas",
    "Color": "#ff0800",
    "Volumen de Exportacion": null,
    "Monto de Importacion": null
  },
  {
    "id_adu": "54",
    "Fecha": "2015/06",
    "Monto de Exportacion": 51793165,
    "Volumen de Importacion": 77,
    "Clave": "26",
    "Tipo_Frontera": "NORTE",
    "Aduana": "Puerto Palomas",
    "Color": "#ff0800",
    "Volumen de Exportacion": null,
    "Monto de Importacion": null
  },
  {
    "id_adu": "54",
    "Fecha": "2015/07",
    "Monto de Exportacion": 77277298.0741,
    "Volumen de Importacion": 82.7098370174,
    "Clave": "26",
    "Tipo_Frontera": "NORTE",
    "Aduana": "Puerto Palomas",
    "Color": "#ff0800",
    "Volumen de Exportacion": null,
    "Monto de Importacion": null
  },
  {
    "id_adu": "54",
    "Fecha": "2015/08",
    "Monto de Exportacion": 113454229.875,
    "Volumen de Importacion": 110.743909336,
    "Clave": "26",
    "Tipo_Frontera": "NORTE",
    "Aduana": "Puerto Palomas",
    "Color": "#ff0800",
    "Volumen de Exportacion": null,
    "Monto de Importacion": null
  },
  {
    "id_adu": "54",
    "Fecha": "2015/09",
    "Monto de Exportacion": 151880428.995,
    "Volumen de Importacion": 150.90372643,
    "Clave": "26",
    "Tipo_Frontera": "NORTE",
    "Aduana": "Puerto Palomas",
    "Color": "#ff0800",
    "Volumen de Exportacion": null,
    "Monto de Importacion": null
  },
  {
    "id_adu": "54",
    "Fecha": "2015/10",
    "Monto de Exportacion": 239139582.421,
    "Volumen de Importacion": 354.598992288,
    "Clave": "26",
    "Tipo_Frontera": "NORTE",
    "Aduana": "Puerto Palomas",
    "Color": "#ff0800",
    "Volumen de Exportacion": null,
    "Monto de Importacion": null
  },
  {
    "id_adu": "54",
    "Fecha": "2015/11",
    "Monto de Exportacion": 257567682.766,
    "Volumen de Importacion": 659.014799489,
    "Clave": "26",
    "Tipo_Frontera": "NORTE",
    "Aduana": "Puerto Palomas",
    "Color": "#ff0800",
    "Volumen de Exportacion": null,
    "Monto de Importacion": null
  },
  {
    "id_adu": "54",
    "Fecha": "2015/12",
    "Monto de Exportacion": 248965808.637,
    "Volumen de Importacion": 1060.15143809,
    "Clave": "26",
    "Tipo_Frontera": "NORTE",
    "Aduana": "Puerto Palomas",
    "Color": "#ff0800",
    "Volumen de Exportacion": null,
    "Monto de Importacion": null
  },
  {
    "id_adu": "54",
    "Fecha": "2016/01",
    "Monto de Exportacion": 70561735.1401,
    "Volumen de Importacion": 932.4073384,
    "Clave": "26",
    "Tipo_Frontera": "NORTE",
    "Aduana": "Puerto Palomas",
    "Color": "#ff0800",
    "Volumen de Exportacion": null,
    "Monto de Importacion": null
  },
  {
    "id_adu": "54",
    "Fecha": "2016/02",
    "Monto de Exportacion": 90586420.4653,
    "Volumen de Importacion": 1693.86059684,
    "Clave": "26",
    "Tipo_Frontera": "NORTE",
    "Aduana": "Puerto Palomas",
    "Color": "#ff0800",
    "Volumen de Exportacion": null,
    "Monto de Importacion": null
  },
  {
    "id_adu": "54",
    "Fecha": "2016/03",
    "Monto de Exportacion": 90074433.0029,
    "Volumen de Importacion": 2420.12137807,
    "Clave": "26",
    "Tipo_Frontera": "NORTE",
    "Aduana": "Puerto Palomas",
    "Color": "#ff0800",
    "Volumen de Exportacion": null,
    "Monto de Importacion": null
  },
  {
    "id_adu": "54",
    "Fecha": "2016/04",
    "Monto de Exportacion": 87512764.5417,
    "Volumen de Importacion": 2371.38928213,
    "Clave": "26",
    "Tipo_Frontera": "NORTE",
    "Aduana": "Puerto Palomas",
    "Color": "#ff0800",
    "Volumen de Exportacion": null,
    "Monto de Importacion": null
  },
  {
    "id_adu": "54",
    "Fecha": "2016/05",
    "Monto de Exportacion": 58954572.3071,
    "Volumen de Importacion": 3194.35600409,
    "Clave": "26",
    "Tipo_Frontera": "NORTE",
    "Aduana": "Puerto Palomas",
    "Color": "#ff0800",
    "Volumen de Exportacion": null,
    "Monto de Importacion": null
  },
  {
    "id_adu": "54",
    "Fecha": "2016/06",
    "Monto de Exportacion": 65511855.4904,
    "Volumen de Importacion": 4284.73214577,
    "Clave": "26",
    "Tipo_Frontera": "NORTE",
    "Aduana": "Puerto Palomas",
    "Color": "#ff0800",
    "Volumen de Exportacion": null,
    "Monto de Importacion": null
  }
]
